{
  "entityType" : "NOTIFICATION_RULE",
  "entity" : {
    "additionalConfig" : {
      "description" : "Send notification to tenant admins when comment is added by user on active alarm"
    },
    "enabled" : true,
    "externalId" : null,
    "id" : {
      "entityType" : "NOTIFICATION_RULE",
      "id" : "d2fe7820-1913-11ef-99a5-817e07e50059"
    },
    "name" : "Comment on active alarm",
    "recipientsConfig" : {
      "targets" : [ "d2fa0b50-1913-11ef-99a5-817e07e50059" ],
      "triggerType" : "ALARM_COMMENT"
    },
    "templateId" : {
      "entityType" : "NOTIFICATION_TEMPLATE",
      "id" : "d2fe2a00-1913-11ef-99a5-817e07e50059"
    },
    "triggerConfig" : {
      "triggerType" : "ALARM_COMMENT",
      "alarmSeverities" : null,
      "alarmStatuses" : [ "ACTIVE" ],
      "alarmTypes" : null,
      "notifyOnCommentUpdate" : false,
      "onlyUserComments" : true,
      "triggerType" : "ALARM_COMMENT"
    },
    "triggerType" : "ALARM_COMMENT"
  },
  "relations" : [ ],
  "attributes" : {
    "SERVER_SCOPE" : [ ]
  }
}